setup.py
bin/pcss
pythoniccss.egg-info/PKG-INFO
pythoniccss.egg-info/SOURCES.txt
pythoniccss.egg-info/dependency_links.txt
pythoniccss.egg-info/requires.txt
pythoniccss.egg-info/top_level.txt
src/pythoniccss/__init__.py
src/pythoniccss/command.py
src/pythoniccss/grammar.py
src/pythoniccss/model.py
src/pythoniccss/processor.py
src/pythoniccss/rgb.txt
src/pythoniccss/writer.py