Metadata-Version: 1.1
Name: pythoniccss
Version: 0.7.0
Summary: A Pythonic CSS pre-processor, designed as a replacement/upgrade to CleverCSS.
